Topsis_Aditya_102003424/Aditya_102003424.py
Topsis_Aditya_102003424-0.8.dist-info/METADATA
Topsis_Aditya_102003424-0.8.dist-info/WHEEL
Topsis_Aditya_102003424-0.8.dist-info/entry_points.txt
Topsis_Aditya_102003424-0.8.dist-info/top_level.txt
Topsis_Aditya_102003424-0.8.dist-info/RECORD
