Metadata-Version: 2.1
Name: Topsis-Aditya-102003424
Version: 0.8
Summary: This is a topsis package of version 0.8
Author: Aditya Singh Rathore
Author-email: arathore_be20@thapar.edu
License: UNKNOWN
Platform: UNKNOWN
Requires-Dist: pandas
